{
    "type": "entity",
    "mixins": "stonehearth:trees:oak:sapling",
    "components": {
        "model_variants": {
            "default": {
                "models": [
               "file(sapling_orange_tree.qb)"
            ]
            }
        },
        "stonehearth:entity_forms": {
            "iconic_form": "file(sapling_orange_tree_iconic.json)",
            "ghost_form": "file(sapling_orange_tree_ghost.json)",
            "placeable_on_ground": true,
            "hide_placement_ui": true
        },
        "stonehearth:evolve": {},
        "stonehearth:resource_node": {
            "resource": "stonehearth:resources:wood:oak_log",
            "durability": 2
        },
        "render_info": {
            "scale": 0.6
        },
        "destination": {
            "region": [
                {
                    "min": {
                        "x": -2,
                        "y": 0,
                        "z": -2
                    },
                    "max": {
                        "x": 2,
                        "y": 1,
                        "z": 2
                    }
            }
         ]
        },
        "region_collision_shape": {
            "region": [
                {
                    "min": {
                        "x": -2,
                        "y": 0,
                        "z": -2
                    },
                    "max": {
                        "x": 2,
                        "y": 6,
                        "z": 2
                    }
            }
         ]
        }
    },
    "entity_data": {
        "stonehearth:evolve_data": {
            "next_stage": "box_o_vox:entities:trees:orange:small",
            "evolve_time": "1d"
        },
        "stonehearth:net_worth": {
            "value_in_gold": 1,
            "rarity": "common",
            "shop_info": {
                "buyable": false,
                "sellable": true,
                "shopkeeper_type": "caravan"
            }
        },
        "stonehearth:catalog": {
            "display_name": "i18n(box_o_vox:entities.trees.orange_tree.sapling_orange_tree.display_name)",
            "description": "i18n(box_o_vox:entities.trees.orange_tree.sapling_orange_tree.description)",
            "category": "plants",
            "material_tags": "plant tree stockpile_plant",
            "icon": "/box_o_vox/entities/trees/images/sapling_orange_tree.png",
            "subject_override": "stonehearth:trees:orange:large"
        },
        "stonehearth:appeal": {
            "appeal": 1
        }
    }
}
