{
   "type": "index",
   "thoughts": {
      "weather": {
         "mutually_exclusive": false,
         "values": {
            "enchanted_mist_positive": {
               "display_name": "Mysterious mist",
               "tooltip": "I wonder what wonders lie beneath that mysterious mist.",
               "duration": "1h",
               "happiness_delta": 10,
               "stackable": true
            },
            "enchanted_mist_negative": {
               "display_name": "Spooky fog",
               "tooltip": "What was that noise in the fog?",
               "duration": "1h",
               "happiness_delta": -1,
               "stackable": false
            }
         }
      }
   }
}
